<rdf:RDF
    xmlns:rdf="http://www.w3.org/1999/02/22-rdf-syntax-ns#"
    xmlns:j.0="http://purl.org/dc/terms/"
    xmlns:j.1="http://www.w3.org/ns/dcat#" > 
  <rdf:Description rdf:about="https://wholepersonproject.github.io/wpp-kg/wpp/dental-and-craniofacial-system">
    <j.1:dataset rdf:resource="https://wholepersonproject.github.io/wpp-kg/wpp/dental-and-craniofacial-system/draft"/>
    <j.0:title xml:lang="en">https://wholepersonproject.github.io/wpp-kg/wpp/dental-and-craniofacial-system</j.0:title>
    <rdf:type rdf:resource="http://www.w3.org/ns/dcat#Catalog"/>
  </rdf:Description>
  <rdf:Description rdf:about="https://wholepersonproject.github.io/wpp-kg/wpp/dental-and-craniofacial-system/draft">
    <j.0:title xml:lang="en">draft</j.0:title>
    <rdf:type rdf:resource="http://www.w3.org/ns/dcat#Dataset"/>
  </rdf:Description>
</rdf:RDF>
